closure/__init__.py
closure/closure.py
closure/hnc.py
closure_problem-2020.5.2.dist-info/LICENSE.md
closure_problem-2020.5.2.dist-info/METADATA
closure_problem-2020.5.2.dist-info/WHEEL
closure_problem-2020.5.2.dist-info/top_level.txt
closure_problem-2020.5.2.dist-info/RECORD
